Metadata-Version: 2.2
Name: tsuz_search
Version: 0.1.2
Summary: A Python client for the tasnif.soliq.uz search API
Author-email: Aslon Khamidov <hamidovaslon1@gmail.com>
License: MIT
Requires-Python: >=3.8
Requires-Dist: requests>=2.25.0
Requires-Dist: pydantic>=2.0.0
Provides-Extra: dev
Requires-Dist: pytest>=7.0.0; extra == "dev"
Requires-Dist: pytest-cov>=4.0.0; extra == "dev"
Requires-Dist: black>=23.0.0; extra == "dev"
Requires-Dist: isort>=5.0.0; extra == "dev"
